tokenflow/__init__.py
tokenflow/tokenflow.py
tokenflow-0.1.0.dist-info/AUTHORS.rst
tokenflow-0.1.0.dist-info/LICENSE
tokenflow-0.1.0.dist-info/METADATA
tokenflow-0.1.0.dist-info/WHEEL
tokenflow-0.1.0.dist-info/top_level.txt
tokenflow-0.1.0.dist-info/RECORD
