Metadata-Version: 2.1
Name: tokenflow
Version: 0.1.0
Summary: tokenizer
Home-page: https://github.com/howl-anderson/tokenflow
Author: Xiaoquan Kong
Author-email: u1mail2me@gmail.com
License: Apache Software License 2.0
Keywords: tokenflow
Platform: UNKNOWN
Classifier: Development Status :: 2 - Pre-Alpha
Classifier: Intended Audience :: Developers
Classifier: License :: OSI Approved :: Apache Software License
Classifier: Natural Language :: English
Classifier: Programming Language :: Python :: 3
Classifier: Programming Language :: Python :: 3.5
Classifier: Programming Language :: Python :: 3.6
Classifier: Programming Language :: Python :: 3.7
Classifier: Programming Language :: Python :: 3.8
Requires-Python: >=3.5
